{
    "fluentMethods": true,
    "relationships": [
        {
            "relationshipName": "item",
            "otherEntityName": "item",
            "relationshipType": "many-to-one",
            "otherEntityField": "name"
        }
    ],
    "fields": [
        {
            "fieldName": "url",
            "fieldType": "String"
        },
        {
            "fieldName": "description",
            "fieldType": "String"
        }
    ],
    "changelogDate": "20161129132336",
    "dto": "no",
    "service": "no",
    "entityTableName": "link",
    "pagination": "no"
}
